cvectors/__init__.py
cvectors/py.typed
cvectors-9.1.2.dist-info/LICENSE
cvectors-9.1.2.dist-info/WHEEL
cvectors-9.1.2.dist-info/METADATA
cvectors-9.1.2.dist-info/RECORD
