Metadata-Version: 2.3
Name: cvectors
Version: 9.1.2
Summary: A simple complex vector package.
Author: Tom Fryers
Requires-Python: >=3.9
Classifier: Development Status :: 5 - Production/Stable
Classifier: Programming Language :: Python :: 3
Classifier: License :: OSI Approved :: GNU General Public License v3 or later (GPLv3+)
Classifier: Operating System :: OS Independent
Project-URL: Homepage, https://gitlab.com/Tom_Fryers/cvectors
